central_system/__init__.py
central_system/client.py
central_system/exception.py
central_system-1.0.2.dist-info/LICENSE
central_system-1.0.2.dist-info/METADATA
central_system-1.0.2.dist-info/WHEEL
central_system-1.0.2.dist-info/top_level.txt
central_system-1.0.2.dist-info/RECORD
