Metadata-Version: 2.1
Name: central-system
Version: 1.0.2
Summary: retrieve data from centralSystem.org
Home-page: UNKNOWN
Author: centralSystem.org
Author-email: opensource@centralSystem.org
License: UNKNOWN
Platform: UNKNOWN
Classifier: Programming Language :: Python :: 3
Classifier: License :: OSI Approved :: MIT License
Classifier: Operating System :: OS Independent
Requires-Python: >=3
License-File: LICENSE
Requires-Dist: requests
Requires-Dist: pandas
Requires-Dist: httpx
Requires-Dist: logging
